CHI/__init__.py
CHI/chi_cache_object.py
CHI/chi_driver.py
CHI/chi_driver_memcache.py
CHI/chi_driver_redis.py
CHI/chi_driver_redis_cluster.py
CHI/chi_util.py
CHI/exception.py
python_perl_chi-0.2.1.data/scripts/chi
python_perl_chi-0.2.1.dist-info/LICENSE
python_perl_chi-0.2.1.dist-info/METADATA
python_perl_chi-0.2.1.dist-info/WHEEL
python_perl_chi-0.2.1.dist-info/top_level.txt
python_perl_chi-0.2.1.dist-info/RECORD
