Metadata-Version: 2.1
Name: python-perl-chi
Version: 0.2.1
Summary: python-perl-chi - Унифицированный интерфейс обработки кэша
Home-page: https://github.com/darviarush/python-perl-chi
Author: Yaroslav O. Kosmina
Author-email: darviarush@mail.ru
License: MIT
Platform: any
Classifier: Development Status :: 4 - Beta
Classifier: Topic :: Text Processing
Classifier: License :: OSI Approved :: MIT License
Classifier: Operating System :: OS Independent
Classifier: Programming Language :: Python :: 3
Classifier: Programming Language :: Python :: 3.3
Classifier: Programming Language :: Python :: 3.4
Classifier: Programming Language :: Python :: 3.5
Classifier: Programming Language :: Python :: 3.6
Classifier: Programming Language :: Python :: 3.7
Requires-Python: >=3.6
License-File: LICENSE
Requires-Dist: argparse
Requires-Dist: data-printer
Requires-Dist: redis-py-cluster
Requires-Dist: redis
Requires-Dist: pymemcache
